README.md
setup.py
lib_test_pytools.egg-info/PKG-INFO
lib_test_pytools.egg-info/SOURCES.txt
lib_test_pytools.egg-info/dependency_links.txt
lib_test_pytools.egg-info/not-zip-safe
lib_test_pytools.egg-info/requires.txt
lib_test_pytools.egg-info/top_level.txt
libpythonpro/__init__.py
libpythonpro/github_api.py